pyva/Application.py
pyva/Global.py
pyva/GlobalInit.py
pyva/__init__.py
pyva/startupApp.py
pyva/cli/__init__.py
pyva/cli/main.py
pyva/client/__init__.py
pyva/client/dingtalk/DingtalkContactClient.py
pyva/client/dingtalk/DingtalkOauth2Client.py
pyva/client/dingtalk/DingtalkRobotClient.py
pyva/client/dingtalk/DingtalkYidaClient.py
pyva/client/dingtalk/__init__.py
pyva/client/feishu/FeishuRobotClient.py
pyva/client/feishu/__init__.py
pyva/common/FastapiEvents.py
pyva/common/FastapiException.py
pyva/common/FilterConditionEnum.py
pyva/common/LoggerHandler.py
pyva/common/OrderConditionEnum.py
pyva/common/RequestLogRoute.py
pyva/common/RequestLogStatusEnum.py
pyva/common/RequestLogTypeEnum.py
pyva/common/__init__.py
pyva/config/AppConfig.py
pyva/config/DbConfig.py
pyva/config/DingtalkConfig.py
pyva/config/DingtalkRobotConfig.py
pyva/config/FastapiConfig.py
pyva/config/FeishuRobotConfig.py
pyva/config/LoggingConfig.py
pyva/config/MongoConfig.py
pyva/config/NacosConfig.py
pyva/config/RedisConfig.py
pyva/config/__init__.py
pyva/dao/BaseDao.py
pyva/dao/ListDao.py
pyva/dao/__init__.py
pyva/dto/BaseDto.py
pyva/dto/ListDto.py
pyva/dto/__init__.py
pyva/entity/BaseEntity.py
pyva/entity/GeneralHumpEntity.py
pyva/entity/HumpEntity.py
pyva/entity/RequestLog.py
pyva/entity/__init__.py
pyva/service/RequestLogService.py
pyva/service/__init__.py
pyva/util/ConfigUtil.py
pyva/util/DbUtil.py
pyva/util/DictUtil.py
pyva/util/EntityUtil.py
pyva/util/FileUtil.py
pyva/util/IpUtil.py
pyva/util/JsonUtil.py
pyva/util/LockerUtil.py
pyva/util/MongoUtil.py
pyva/util/NacosUtil.py
pyva/util/PathUtil.py
pyva/util/QrcodeUtil.py
pyva/util/RedisUtil.py
pyva/util/TimeUtil.py
pyva/util/__init__.py
pyva_framework-3.3.16.dist-info/LICENSE
pyva_framework-3.3.16.dist-info/METADATA
pyva_framework-3.3.16.dist-info/WHEEL
pyva_framework-3.3.16.dist-info/entry_points.txt
pyva_framework-3.3.16.dist-info/top_level.txt
pyva_framework-3.3.16.dist-info/RECORD
