Metadata-Version: 2.1
Name: pyva-framework
Version: 3.3.16
Summary: PyVa = Python项目 + Java风格，这是一个工程框架库，包含DB、Redis、MongoDB、JSON等工具和基础服务类。
Home-page: https://github.com/zhenqiang-sun/pyva
Author: Zhenqiang Sun
Author-email: zhenqiang.sun@gmail.com
Classifier: Programming Language :: Python :: 3
Classifier: License :: OSI Approved :: MIT License
Classifier: Operating System :: OS Independent
Requires-Python: >=3.10
License-File: LICENSE
Requires-Dist: fastapi==0.112.1
Requires-Dist: uvicorn==0.30.6
Requires-Dist: SQLAlchemy==2.0.32
Requires-Dist: PyMySQL==1.1.1
Requires-Dist: sqlacodegen==3.0.0rc5
Requires-Dist: redis==5.1.0b5
Requires-Dist: requests==2.32.3
Requires-Dist: pyhumps==3.8.0
Requires-Dist: nacos-sdk-python==1.0.0
Requires-Dist: PyYAML==6.0.2
Requires-Dist: python-multipart==0.0.9
Requires-Dist: pymongo==4.8.0
Requires-Dist: orjson==3.10.7
Requires-Dist: openpyxl==3.2.0b1
Requires-Dist: deprecated==1.2.14
Requires-Dist: jinja2==3.1.4
Requires-Dist: typer[all]==0.12.3
Requires-Dist: py-ulid==1.0.3
